whitex/__init__.py
whitex/cli.py
whitex/commands.py
whitex/whitex.py
whitex-0.0.5.dist-info/AUTHORS.rst
whitex-0.0.5.dist-info/LICENSE
whitex-0.0.5.dist-info/METADATA
whitex-0.0.5.dist-info/WHEEL
whitex-0.0.5.dist-info/entry_points.txt
whitex-0.0.5.dist-info/top_level.txt
whitex-0.0.5.dist-info/RECORD
