Metadata-Version: 2.1
Name: whitex
Version: 0.0.5
Summary: Clean up LaTeX files
Home-page: https://github.com/ivanovmg/whitex
Author: Maxim Ivanov
Author-email: ivanovmg@gmail.com
License: GNU General Public License v3
Keywords: whitex
Platform: UNKNOWN
Classifier: Development Status :: 3 - Alpha
Classifier: Intended Audience :: Developers
Classifier: Intended Audience :: Education
Classifier: Intended Audience :: Science/Research
Classifier: License :: OSI Approved :: GNU General Public License v3 (GPLv3)
Classifier: Natural Language :: English
Classifier: Topic :: Text Processing :: Markup :: LaTeX
Classifier: Programming Language :: Python :: 3
Classifier: Programming Language :: Python :: 3.6
Classifier: Programming Language :: Python :: 3.7
Classifier: Programming Language :: Python :: 3.8
Requires-Python: >=3.6
Requires-Dist: Click (>=7.0)
